{
  "805420102409256991": {
    "actions": [
      {
        "action": "register",
        "file": "PNB V2",
        "userid": "826404",
        "growid": "Mitsuzanee"
      },
      {
        "action": "delete",
        "file": "TEST",
        "userid": "323102"
      },
      {
        "action": "delete",
        "file": "TEST",
        "userid": "323293"
      },
      {
        "action": "register",
        "file": "PNB V2",
        "userid": "839887",
        "growid": "nsps3"
      },
      {
        "action": "change",
        "file": "PNB V2",
        "userid": "from: 779081 to: 776267",
        "growid": "JoHo"
      }
    ]
  },
  "590156274117771295": {
    "actions": [
      {
        "action": "register",
        "file": "PNB V2",
        "userid": "323293",
        "growid": "CyN4STY"
      },
      {
        "action": "register",
        "file": "PTHT V2",
        "userid": "323293",
        "growid": "CyN4STY"
      },
      {
        "action": "register",
        "file": "PNB V2",
        "userid": "826404",
        "growid": "Mitsuzanee"
      },
      {
        "action": "register",
        "file": "PTHT V2",
        "userid": "712785",
        "growid": "FarmerBus"
      }
    ]
  }
}